aws_batch_helpers/__init__.py
aws_batch_helpers/_version.py
aws_batch_helpers/aws_batch_helpers.py
aws_batch_helpers/aws_s3_helpers.py
aws_batch_helpers-0.18.0.dist-info/AUTHORS.rst
aws_batch_helpers-0.18.0.dist-info/LICENSE
aws_batch_helpers-0.18.0.dist-info/METADATA
aws_batch_helpers-0.18.0.dist-info/WHEEL
aws_batch_helpers-0.18.0.dist-info/top_level.txt
aws_batch_helpers-0.18.0.dist-info/RECORD
