Metadata-Version: 2.1
Name: aws-batch-helpers
Version: 0.18.0
Summary: Helpers for running jobs on AWS Batch
Home-page: https://github.com/jerowe/aws_batch_helpers
Author: Jillian Rowe
Author-email: jillian.e.rowe@gmail.com
License: MIT license
Keywords: aws_batch_helpers
Platform: UNKNOWN
Classifier: Development Status :: 2 - Pre-Alpha
Classifier: Intended Audience :: Developers
Classifier: License :: OSI Approved :: MIT License
Classifier: Natural Language :: English
Classifier: Programming Language :: Python :: 3
Classifier: Programming Language :: Python :: 3.6
Classifier: Programming Language :: Python :: 3.7
Classifier: Programming Language :: Python :: 3.8
Requires-Python: >=3.6
License-File: LICENSE
License-File: AUTHORS.rst
Requires-Dist: boto3
Requires-Dist: typing-extensions (==3.10.0.2)
Requires-Dist: typing-inspect (==0.7.1)
Requires-Dist: mypy-boto3-batch (==1.21.0)
Requires-Dist: mypy-boto3-s3 (==1.21.0)
Requires-Dist: mypy-boto3-logs (==1.21.0)
Requires-Dist: mypy-boto3-ec2 (==1.21.0)
